{"1":{"1":{"en":"By the racers","ru_ref":"Kлянусь мчащимися,"},"2":{"en":"panting","ru_ref":"запыхаясь,"}},"2":{"1":{"en":"And the producers of sparks","ru_ref":"и высекающими"},"2":{"en":"striking","ru_ref":"искры"}},"3":{"1":{"en":"And the chargers","ru_ref":"и нападающими"},"2":{"en":"(at) dawn","ru_ref":"на заре"}},"4":{"1":{"en":"Then raise","ru_ref":"поднимающими [досл. и они подняли]"},"2":{"en":"thereby","ru_ref":"этим"},"3":{"en":"dust","ru_ref":"пыль,"}},"5":{"1":{"en":"Then penetrate (in the) center","ru_ref":"врывающимися [досл. и ворвались] в середину"},"2":{"en":"thereby","ru_ref":"с ним [с пылью]"},"3":{"en":"collectively","ru_ref":"в толпу"}},"6":{"1":{"en":"Indeed","ru_ref":"Поистине,","ru":"поистине"},"2":{"en":"mankind","ru_ref":"человек"},"3":{"en":"to his Lord","ru_ref":"по отношению к своему Господу"},"4":{"en":"(is) surely ungrateful","ru_ref":"конечно же, неблагодарен,"}},"7":{"1":{"en":"And indeed, he","ru_ref":"и поистине, Он"},"2":{"en":"on","ru_ref":"на","ru":"на"},"3":{"en":"that","ru_ref":"это","ru":"что"},"4":{"en":"surely (is) a witness","ru_ref":"конечно же, свидетель!"}},"8":{"1":{"en":"And indeed he","ru_ref":"И, поистине, он"},"2":{"en":"in (the) love","ru_ref":"в любви"},"3":{"en":"(of) wealth","ru_ref":"к благам"},"4":{"en":"(is) surely intense","ru_ref":"конечно же силен!"}},"9":{"1":{"en":"But does not","ru_ref":"Разве не"},"2":{"en":"he know","ru_ref":"знает он,"},"3":{"en":"when","ru_ref":"когда","ru":"когда"},"4":{"en":"will be scattered","ru_ref":"будет изведено"},"5":{"en":"what","ru_ref":"то, что","ru":"что"},"6":{"en":"(is) in","ru_ref":"в","ru":"в"},"7":{"en":"the graves","ru_ref":"могилах"}},"10":{"1":{"en":"And is made apparent","ru_ref":"и будет представлено"},"2":{"en":"what","ru_ref":"то, что","ru":"что"},"3":{"en":"(is) in","ru_ref":"в","ru":"в"},"4":{"en":"the breasts","ru_ref":"грудях"}},"11":{"1":{"en":"Indeed","ru_ref":"Поистине,","ru":"поистине"},"2":{"en":"their Lord","ru_ref":"Господь их","ru":"их Господь"},"3":{"en":"about them","ru_ref":"о них"},"4":{"en":"that Day","ru_ref":"в тот день"},"5":{"en":"(is) surely All-Aware","ru_ref":"конечно же, осведомлен"}}}