{"1":{"1":{"en":"Glorifies","ru_ref":"Восславляют","ru":"хвалит"},"2":{"en":"Allah","ru_ref":"Аллаха","ru":"Аллаха"},"3":{"en":"whatever","ru_ref":"то, что","ru":"то, что"},"4":{"en":"(is) in","ru_ref":"в","ru":"в"},"5":{"en":"the heavens","ru_ref":"небесах,","ru":"небесах"},"6":{"en":"and whatever","ru_ref":"и то, что","ru":"и то, что"},"7":{"en":"(is) in","ru_ref":"на","ru":"в"},"8":{"en":"the earth","ru_ref":"земле,","ru":"земле"},"9":{"en":"the Sovereign","ru_ref":"Владыку,","ru":"царя"},"10":{"en":"the Holy","ru_ref":"Святого,","ru":"святого"},"11":{"en":"the All-Mighty","ru_ref":"Величественного,","ru":"великого"},"12":{"en":"the All-Wise","ru_ref":"Мудрого!","ru":"мудрого"}},"2":{"1":{"en":"He","ru_ref":"Он –","ru":"Он"},"2":{"en":"(is) the One Who","ru_ref":"Тот, Который","ru":"тот, кто"},"3":{"en":"sent","ru_ref":"послал","ru":"послал"},"4":{"en":"among","ru_ref":"к","ru":"среди"},"5":{"en":"the unlettered","ru_ref":"неграмотным","ru":"простецов"},"6":{"en":"a Messenger","ru_ref":"посланника","ru":"посланника"},"7":{"en":"from themselves","ru_ref":"из их числа же","ru":"из них"},"8":{"en":"reciting","ru_ref":"который читает","ru":"он читает"},"9":{"en":"to them","ru_ref":"им","ru":"им"},"10":{"en":"His Verses","ru_ref":"Его знамения","ru":"Его знамения"},"11":{"en":"and purifying them","ru_ref":"и очищает их","ru":"и очищает их"},"12":{"en":"and teaching them","ru_ref":"и обучает их","ru":"и обучает их"},"13":{"en":"the Book","ru_ref":"Книге","ru":"писанию"},"14":{"en":"and the wisdom","ru_ref":"и мудрости","ru":"и мудрости"},"15":{"en":"although","ru_ref":"хотя","ru":"хотя"},"16":{"en":"they were","ru_ref":"они были,","ru":"они были"},"17":{"en":"from","ru_ref":"раньше","ru":"—"},"18":{"en":"before","ru":"раньше"},"19":{"en":"surely in","ru_ref":"однозначно, в","ru":"конечно в"},"20":{"en":"an error","ru_ref":"заблуждении","ru":"заблуждении"},"21":{"en":"clear","ru_ref":"явном.","ru":"явном"}},"3":{"1":{"en":"And others","ru_ref":"И другим","ru":"и других"},"2":{"en":"among them","ru_ref":"из них (которые)","ru":"из них"},"3":{"en":"who have not yet","ru_ref":"ещё не","ru":"которые еще не"},"4":{"en":"joined","ru_ref":"присоединились","ru":"присоединились"},"5":{"en":"them","ru_ref":"к ним","ru":"к ним"},"6":{"en":"and He","ru_ref":"И Он –","ru":"и Он"},"7":{"en":"(is) the All-Mighty","ru_ref":"Величественный,","ru":"великий"},"8":{"en":"the All-Wise","ru_ref":"Мудрый!","ru":"мудрый"}},"4":{"1":{"en":"That","ru_ref":"Это –","ru":"это"},"2":{"en":"(is the) Bounty","ru_ref":"щедрость","ru":"милость"},"3":{"en":"(of) Allah","ru_ref":"Аллаха,","ru":"Аллаха"},"4":{"en":"He gives it","ru_ref":"которую дарует Он,","ru":"дарует Он ее"},"5":{"en":"(to) whom","ru_ref":"кому","ru":"тому, кому"},"6":{"en":"He wills","ru_ref":"пожелает.","ru":"пожелает"},"7":{"en":"And Allah","ru_ref":"И Аллах","ru":"и Аллах"},"8":{"en":"(is the) Possessor","ru_ref":"обладатель","ru":"обладатель"},"9":{"en":"(of) Bounty","ru_ref":"щедрости","ru":"милости"},"10":{"en":"the Great","ru_ref":"великой.","ru":"великой"}},"5":{"1":{"en":"(The) likeness","ru_ref":"Пример","ru":"подобие"},"2":{"en":"(of) those who","ru_ref":"тех,","ru":"тех, кому"},"3":{"en":"were entrusted","ru_ref":"было возложено на которых","ru":"было дано нести"},"4":{"en":"(with) the Taurat","ru_ref":"(следование) Торе","ru":"Тору"},"5":{"en":"then","ru_ref":"затем","ru":"потом"},"6":{"en":"not","ru_ref":"не","ru":"не"},"7":{"en":"they bore it","ru_ref":"понесли её","ru":"понесли они ее"},"8":{"en":"(is) like","ru_ref":"подобен примеру","ru":"подобно"},"9":{"en":"the donkey","ru_ref":"осла,","ru":"ослу"},"10":{"en":"who carries","ru_ref":"который везет","ru":"который несет"},"11":{"en":"books","ru_ref":"книги.","ru":"книги"},"12":{"en":"Wretched is","ru_ref":"Как плох","ru":"скверно"},"13":{"en":"(the) example","ru_ref":"пример","ru":"подобие"},"14":{"en":"(of) the people","ru_ref":"людей,","ru":"людей"},"15":{"en":"who","ru_ref":"которые","ru":"которые"},"16":{"en":"deny","ru_ref":"сочли ложью","ru":"считали ложью"},"17":{"en":"(the) Signs","ru_ref":"знамения","ru":"знамения"},"18":{"en":"(of) Allah","ru_ref":"Аллаха!","ru":"Аллаха"},"19":{"en":"And Allah","ru_ref":"И Аллах","ru":"и Аллах"},"20":{"en":"(does) not","ru_ref":"не","ru":"не"},"21":{"en":"guide","ru_ref":"ведет","ru":"ведет прямо"},"22":{"en":"the people","ru_ref":"людей (которые)","ru":"людей"},"23":{"en":"the wrongdoers","ru_ref":"(являются) притеснителями.","ru":"неправедных"}},"6":{"1":{"en":"Say","ru_ref":"Скажи:","ru":"скажи"},"2":{"en":"O","ru_ref":"«О","ru":"о"},"3":{"en":"you (who)","ru_ref":"те, которые","ru":"вы, которые"},"4":{"en":"(are) Jews","ru_ref":"стали иудеями!","ru":"стали иудеями"},"5":{"en":"If","ru_ref":"Если","ru":"если"},"6":{"en":"you claim","ru_ref":"вы утверждаете,","ru":"вы утверждаете"},"7":{"en":"that you","ru_ref":"что вы","ru":"что вы"},"8":{"en":"(are) allies","ru_ref":"сторонники","ru":"близкие"},"9":{"en":"of Allah","ru_ref":"Аллаха","ru":"к Аллаху"},"10":{"en":"from","ru_ref":"помимо","ru":"—"},"11":{"en":"excluding","ru_ref":"других","ru":"помимо прочих"},"12":{"en":"the people","ru_ref":"людей,","ru":"людей"},"13":{"en":"then wish","ru_ref":"то пожелайте","ru":"то пожелайте"},"14":{"en":"(for) the death","ru_ref":"смерти,","ru":"смерти"},"15":{"en":"if","ru_ref":"если","ru":"если"},"16":{"en":"you are","ru_ref":"вы являетесь","ru":"вы"},"17":{"en":"truthful","ru_ref":"правдивыми!»","ru":"правдивы"}},"7":{"1":{"en":"But not","ru_ref":"Но не","ru":"но не"},"2":{"en":"they will wish for it","ru_ref":"пожелают они её","ru":"пожелают они ее"},"3":{"en":"ever","ru_ref":"никогда","ru":"никогда"},"4":{"en":"for what","ru_ref":"за то,","ru":"за то, что"},"5":{"en":"(have) sent forth","ru_ref":"что уготовали","ru":"уготовали"},"6":{"en":"their hands","ru_ref":"их руки.","ru":"их руки"},"7":{"en":"And Allah","ru_ref":"А Аллах","ru":"и Аллах"},"8":{"en":"(is) All-Knowing","ru_ref":"знает","ru":"знающ"},"9":{"en":"of the wrongdoers","ru_ref":"притеснителей!","ru":"о неправедных"}},"8":{"1":{"en":"Say","ru_ref":"Скажи:","ru":"скажи"},"2":{"en":"Indeed","ru_ref":"«Поистине,","ru":"поистине"},"3":{"en":"the death","ru_ref":"смерть","ru":"смерть"},"4":{"en":"which","ru_ref":"которая","ru":"от которой"},"5":{"en":"you flee","ru_ref":"вы убегаете,","ru":"вы убегаете"},"6":{"en":"from it","ru_ref":"от неё","ru":"от нее"},"7":{"en":"then surely it","ru_ref":"поистине, она","ru":"то поистине она"},"8":{"en":"(will) meet you","ru_ref":"встретит вас.","ru":"встретит вас"},"9":{"en":"Then","ru_ref":"Затем","ru":"потом"},"10":{"en":"you will be sent back","ru_ref":"вы будете возвращены","ru":"вы будете возвращены"},"11":{"en":"to","ru_ref":"к","ru":"к"},"12":{"en":"(the) All-Knower","ru_ref":"Знающему","ru":"знающему"},"13":{"en":"(of) the unseen","ru_ref":"сокровенное","ru":"сокровенное"},"14":{"en":"and the witnessed","ru_ref":"и явное,","ru":"и явное"},"15":{"en":"and He will inform you","ru_ref":"и Он сообщит вам","ru":"и Он сообщит вам"},"16":{"en":"[of] what","ru_ref":"то, что","ru":"то, что"},"17":{"en":"you used to","ru_ref":"вы были","ru":"вы"},"18":{"en":"do","ru_ref":"совершающими».","ru":"делали"}},"9":{"1":{"en":"O","ru_ref":"О","ru":"о"},"2":{"en":"(you) who","ru_ref":"те, которые","ru":"вы, которые"},"3":{"en":"believe","ru_ref":"уверовали!","ru":"уверовали"},"4":{"en":"When","ru_ref":"Когда","ru":"когда"},"5":{"en":"(the) call is made","ru_ref":"призывают","ru":"возглашено"},"6":{"en":"for (the) prayer","ru_ref":"на молитву","ru":"на молитву"},"7":{"en":"on","ru_ref":"в","ru":"в"},"8":{"en":"(the) day","ru_ref":"день","ru":"день"},"9":{"en":"(of) Friday","ru_ref":"пятницы","ru":"собрания"},"10":{"en":"then hasten","ru_ref":"то устремляйтесь","ru":"то устремляйтесь"},"11":{"en":"to","ru_ref":"к","ru":"к"},"12":{"en":"(the) remembrance","ru_ref":"поминанию","ru":"поминанию"},"13":{"en":"(of) Allah","ru_ref":"Аллаха","ru":"Аллаха"},"14":{"en":"and leave","ru_ref":"и оставьте","ru":"и оставьте"},"15":{"en":"the business","ru_ref":"торговлю.","ru":"торговлю"},"16":{"en":"That","ru_ref":"Это –","ru":"это"},"17":{"en":"(is) better","ru_ref":"лучше","ru":"лучше"},"18":{"en":"for you","ru_ref":"для вас,","ru":"для вас"},"19":{"en":"if","ru_ref":"если","ru":"если"},"20":{"en":"you","ru_ref":"вы являетесь","ru":"вы"},"21":{"en":"know","ru_ref":"знающими.","ru":"знаете"}},"10":{"1":{"en":"Then when","ru_ref":"А когда","ru":"а когда"},"2":{"en":"is concluded","ru_ref":"будет кончена","ru":"кончена будет"},"3":{"en":"the prayer","ru_ref":"молитва,","ru":"молитва"},"4":{"en":"then disperse","ru_ref":"то расходитесь","ru":"то расходитесь"},"5":{"en":"in","ru_ref":"по","ru":"по"},"6":{"en":"the land","ru_ref":"земле,","ru":"земле"},"7":{"en":"and seek","ru_ref":"и ищите","ru":"и ищите"},"8":{"en":"from","ru_ref":"от","ru":"из"},"9":{"en":"(the) Bounty","ru_ref":"щедрости","ru":"милости"},"10":{"en":"(of) Allah","ru_ref":"Аллаха,","ru":"Аллаха"},"11":{"en":"and remember","ru_ref":"и поминайте","ru":"и поминайте"},"12":{"en":"Allah","ru_ref":"Аллаха","ru":"Аллаха"},"13":{"en":"much","ru_ref":"много,","ru":"часто"},"14":{"en":"so that you may","ru_ref":"чтобы вы","ru":"может быть, вы"},"15":{"en":"succeed","ru_ref":"преуспели вы.","ru":"будете счастливы"}},"11":{"1":{"en":"And when","ru_ref":"А когда","ru":"а когда"},"2":{"en":"they saw","ru_ref":"они видят","ru":"они увидели"},"3":{"en":"a transaction","ru_ref":"(какую-нибудь) торговлю","ru":"торговлю"},"4":{"en":"or","ru_ref":"или","ru":"или"},"5":{"en":"a sport","ru_ref":"(какую-нибудь) забаву,","ru":"забаву"},"6":{"en":"they rushed","ru_ref":"то устремляются","ru":"они устремились"},"7":{"en":"to it","ru_ref":"к ней","ru":"к ней"},"8":{"en":"and left you","ru_ref":"и оставляют тебя","ru":"и оставили тебя"},"9":{"en":"standing","ru_ref":"стоящим.","ru":"стоящим"},"10":{"en":"Say","ru_ref":"Скажи:","ru":"скажи"},"11":{"en":"What","ru_ref":"«То, что","ru":"то, что"},"12":{"en":"(is) with","ru_ref":"у","ru":"у"},"13":{"en":"Allah","ru_ref":"Аллаха,","ru":"Аллаха"},"14":{"en":"(is) better","ru_ref":"лучше,","ru":"лучше"},"15":{"en":"than","ru_ref":"чем","ru":"чем"},"16":{"en":"the sport","ru_ref":"забава","ru":"забава"},"17":{"en":"and from","ru_ref":"и","ru":"и"},"18":{"en":"(any) transaction","ru_ref":"торговля».","ru":"торговля"},"19":{"en":"And Allah","ru_ref":"И Аллах –","ru":"и Аллах"},"20":{"en":"(is the) Best","ru_ref":"лучший","ru":"лучший"},"21":{"en":"(of) the Providers","ru_ref":"из дающих удел.","ru":"из дающих удел"}}}