{"lines":{"1":[["ﭑ",175],["ﭒ",175],["ﭓ",175],["ﭔ",175],["ﭕ",175],["ﭖ",175],["ﭗ",175],["ﭘ",175],["ﭙ",175],["ﭚ",175],["ﭛﭜ",175],["ﭝ",175],["ﭞ",175]],"2":[["ﭟ",175],["ﭠ",175],["ﭡ",175],["ﭢ",175],["ﭣ",175],["ﭤ",175],["ﭥ",175],["ﭦﭧ",175],["ﭨ",175]],"3":[["ﭩ",175],["ﭪ",175],["ﭫ",175],["ﭬ",175],["ﭭ",175],["ﭮ",175],["ﭯ",175],["ﭰ ﭱ",175],["ﭲ",175],["ﭳ",175]],"4":[["ﭴ",175],["ﭵ",175],["ﭶ",175],["ﭷ",175],["ﭸ",175],["ﭹ",175],["ﭺ",175],["ﭻﭼ",175],["ﭽ",175]],"5":[["ﭾ",175],["ﭿ",175],["ﮀ",175],["ﮁ",175],["ﮂ",175],["ﮃﮄ",175],["ﮅ",175],["ﮆ",175],["ﮇ",175]],"6":[["ﮈ",175],["ﮉ",175],["ﮊ",175],["ﮋ",175],["ﮌ",175],["ﮍ",175],["ﮎ",175],["ﮏ",175],["ﮐ",175]],"7":[["ﮑ",175],["ﮒ",175],["ﮓ",175],["ﮔ",175],["ﮕ",175],["ﮖ",175],["ﮗ",175],["ﮘﮙ",175],["ﮚ",175]],"8":[["ﮛ",175],["ﮜ",175],["ﮝ",175],["ﮞ",175],["ﮟ",175],["ﮠ",175],["ﮡ",175],["ﮢ",175],["ﮣ",175],["ﮤ",175],["ﮥ",175]],"9":[["ﮦ",175],["ﮧ",175],["ﮨ",175],["ﮩ",175],["ﮪ",175],["ﮫ",175],["ﮬ",175],["ﮭ",175],["ﮮ",175]],"10":[["ﮯ",175],["ﮰ",175],["ﮱ",175],["ﯓ",175],["ﯔ",175],["ﯕﯖ",175],["ﯗ",175],["ﯘ",175],["ﯙ",175]],"11":[["ﯚ",175],["ﯛ",175],["ﯜ",175],["ﯝ",175],["ﯞ",175],["ﯟ",175],["ﯠ",175],["ﯡ",175],["ﯢ",175],["ﯣ",175]],"12":[["ﯤ",175],["ﯥﯦ",175],["ﯧ",175],["ﯨ",175],["ﯩ",175],["ﯪ",175]],"13":[["ﯫ",175],["ﯬ",175],["ﯭ",175],["ﯮ",175],["ﯯ",175],["ﯰ",175],["ﯱﯲ",175],["ﯳ",175],["ﯴ",175],["ﯵ",175]],"14":[["ﯶ",175],["ﯷﯸ",175],["ﯹ",175],["ﯺ",175],["ﯻ",175],["ﯼ",175],["ﯽﯾ",175],["ﯿ",175],["ﰀ",175],["ﰁ",175]],"15":[["ﰂ",175],["ﰃﰄ",175],["ﰅ",175],["ﰆ",175],["ﰇ",175],["ﰈ",175],["ﰉ",175],["ﰊ",175],["ﰋ",175],["ﰌ",175]]},"starts":[]}