{"lines":{"1":[["ﭑ",234],["ﭒ",234],["ﭓ",234],["ﭔ",234],["ﭕ",234],["ﭖ",234],["ﭗﭘ",234],["ﭙ",234],["ﭚ",234],["ﭛ",234],["ﭜ",234],["ﭝ",234]],"2":[["ﭞ",234],["ﭟ",234],["ﭠﭡ",234],["ﭢ",234],["ﭣ",234],["ﭤ",234],["ﭥ",234],["ﭦ",234],["ﭧ",234]],"3":[["ﭨ",234],["ﭩ",234],["ﭪ",234],["ﭫ",234],["ﭬ",234],["ﭭﭮ",234],["ﭯ",234],["ﭰ",234]],"4":[["ﭱ",234],["ﭲ",234],["ﭳ",234],["ﭴ",234],["ﭵﭶ",234],["ﭷ",234],["ﭸ",234],["ﭹ",234],["ﭺ",234],["ﭻ",234]],"5":[["ﭼ",234],["ﭽ",234],["ﭾ",234],["ﭿ",234],["ﮀ",234],["ﮁ",234],["ﮂﮃ",234],["ﮄ",234],["ﮅ",234],["ﮆ",234]],"6":[["ﮇ",234],["ﮈ",234],["ﮉ",234],["ﮊ",234],["ﮋ",234],["ﮌ",234],["ﮍ",234],["ﮎ",234],["ﮏ",234],["ﮐﮑ",234]],"7":[["ﮒ",234],["ﮓ",234],["ﮔ",234],["ﮕ",234],["ﮖ",234],["ﮗ",234],["ﮘ",234],["ﮙ",234],["ﮚ",234],["ﮛ",234]],"8":[["ﮜ",234],["ﮝ",234],["ﮞ",234],["ﮟ",234],["ﮠ",234],["ﮡ",234],["ﮢ",234],["ﮣ",234],["ﮤ",234],["ﮥ",234]],"9":[["ﮦ",234],["ﮧ",234],["ﮨ",234],["ﮩ",234],["ﮪ",234],["ﮫ",234],["ﮬ",234],["ﮭ",234],["ﮮ",234]],"10":[["ﮯﮰ",234],["ﮱ",234],["ﯓ",234],["ﯔ",234],["ﯕﯖ",234],["ﯗ",234],["ﯘ",234],["ﯙ",234]],"11":[["ﯚ",234],["ﯛ",234],["ﯜ",234],["ﯝ",234],["ﯞ",234],["ﯟ",234],["ﯠ",234],["ﯡ",234],["ﯢ",234],["ﯣ",234]],"12":[["ﯤ",234],["ﯥ",234],["ﯦ",234],["ﯧ",234],["ﯨ",234],["ﯩ",234],["ﯪ",234],["ﯫ",234],["ﯬ",234],["ﯭ",234]],"13":[["ﯮ",234],["ﯯ",234],["ﯰ",234],["ﯱ",234],["ﯲ",234],["ﯳ",234],["ﯴﯵ",234],["ﯶ",234],["ﯷ",234]],"14":[["ﯸ",234],["ﯹ",234],["ﯺ",234],["ﯻ",234],["ﯼ",234],["ﯽ",234],["ﯾ",234],["ﯿ",234],["ﰀ",234]],"15":[["ﰁ",234],["ﰂ",234],["ﰃ",234],["ﰄ",234],["ﰅ",234],["ﰆ",234],["ﰇ",234]]},"starts":[]}