{"lines":{"1":[["ﭑ",235],["ﭒ",235],["ﭓ",235],["ﭔ",235],["ﭕ",235],["ﭖ",235],["ﭗﭘ",235],["ﭙ",235],["ﭚ",235],["ﭛ",235]],"2":[["ﭜ",235],["ﭝ",235],["ﭞ",235],["ﭟ",235],["ﭠﭡ",235],["ﭢ",235],["ﭣﭤ",235],["ﭥ",235],["ﭦ",235],["ﭧ",235]],"3":[["ﭨ",235],["ﭩ",235],["ﭪ",235],["ﭫ",235],["ﭬ",235],["ﭭ",235],["ﭮ",235],["ﭯ",235],["ﭰ",235]],"4":[["ﭱ",235],["ﭲ",235],["ﭳ",235],["ﭴ",235],["ﭵ",235],["ﭶ",235],["ﭷ",235],["ﭸﭹ",235],["ﭺ",235],["ﭻ",235],["ﭼ",235]],"5":[["ﭽ",235],["ﭾ",235],["ﭿ",235],["ﮀ",235],["ﮁ",235],["ﮂ",235],["ﮃ",235],["ﮄ",235],["ﮅ",235]],"6":[["ﮆ",235],["ﮇ",235],["ﮈ",235],["ﮉ",235],["ﮊ",235],["ﮋ",235],["ﮌ",235],["ﮍ",235],["ﮎ",235]],"7":[["ﮏ",235],["ﮐ",235],["ﮑ",235],["ﮒ",235],["ﮓ",235],["ﮔ",235],["ﮕ",235],["ﮖ",235],["ﮗ",235]],"8":[["ﮘ",235],["ﮙ",235],["ﮚﮛ",235],["ﮜ",235],["ﮝ",235],["ﮞ",235],["ﮟ",235],["ﮠ",235],["ﮡ",235]],"11":[["ﮢﮣ",235],["ﮤ",235],["ﮥ",235],["ﮦ",235],["ﮧ",235],["ﮨ",235],["ﮩ",235],["ﮪ",235],["ﮫ",235],["ﮬ",235]],"12":[["ﮭ",235],["ﮮ",235],["ﮯ",235],["ﮰ",235],["ﮱ",235],["ﯓ",235],["ﯔ",235],["ﯕ",235]],"13":[["ﯖ",235],["ﯗ",235],["ﯘ",235],["ﯙ",235],["ﯚ",235],["ﯛ",235],["ﯜ",235],["ﯝ",235],["ﯞ",235]],"14":[["ﯟ",235],["ﯠ",235],["ﯡ",235],["ﯢ",235],["ﯣ",235],["ﯤ",235],["ﯥ",235],["ﯦ",235],["ﯧ",235],["ﯨ",235]],"15":[["ﯩ",235],["ﯪ",235],["ﯫ",235],["ﯬ",235],["ﯭ",235],["ﯮ",235],["ﯯ",235],["ﯰ",235],["ﯱ",235]]},"starts":[{"surah":12,"ayah":1,"line":11}],"center":[8]}