{"lines":{"1":[["ﭑ",237],["ﭒ",237],["ﭓ",237],["ﭔ",237],["ﭕ",237],["ﭖ",237],["ﭗ",237],["ﭘ",237],["ﭙﭚ",237],["ﭛ",237]],"2":[["ﭜ",237],["ﭝ",237],["ﭞ",237],["ﭟ",237],["ﭠ",237],["ﭡ",237],["ﭢ",237],["ﭣ",237],["ﭤ",237]],"3":[["ﭥ",237],["ﭦ",237],["ﭧ",237],["ﭨ",237],["ﭩ",237],["ﭪ",237],["ﭫ",237],["ﭬ",237],["ﭭ",237]],"4":[["ﭮ",237],["ﭯ",237],["ﭰ",237],["ﭱ",237],["ﭲ",237],["ﭳﭴ",237],["ﭵ",237],["ﭶ",237]],"5":[["ﭷ",237],["ﭸ",237],["ﭹ",237],["ﭺ",237],["ﭻ",237],["ﭼ",237],["ﭽ",237],["ﭾ",237],["ﭿ",237]],"6":[["ﮀ",237],["ﮁﮂ",237],["ﮃ",237],["ﮄ",237],["ﮅ",237],["ﮆ",237],["ﮇ",237],["ﮈﮉ",237],["ﮊ",237],["ﮋﮌ",237]],"7":[["ﮍ",237],["ﮎ",237],["ﮏ",237],["ﮐ",237],["ﮑ",237],["ﮒ",237],["ﮓ",237],["ﮔ",237],["ﮕ",237]],"8":[["ﮖ",237],["ﮗ",237],["ﮘﮙ",237],["ﮚ",237],["ﮛ",237],["ﮜ",237],["ﮝﮞ",237],["ﮟ",237],["ﮠﮡ",237]],"9":[["ﮢ",237],["ﮣ",237],["ﮤ",237],["ﮥ",237],["ﮦ",237],["ﮧ",237],["ﮨ",237],["ﮩ",237]],"10":[["ﮪ",237],["ﮫ",237],["ﮬ",237],["ﮭ",237],["ﮮ",237],["ﮯ",237],["ﮰ",237],["ﮱ",237]],"11":[["ﯓ",237],["ﯔ",237],["ﯕ",237],["ﯖ",237],["ﯗ",237],["ﯘ",237],["ﯙ",237],["ﯚ",237]],"12":[["ﯛ",237],["ﯜ",237],["ﯝ",237],["ﯞ",237],["ﯟﯠ",237],["ﯡ",237],["ﯢ",237],["ﯣ",237],["ﯤ",237]],"13":[["ﯥ",237],["ﯦ",237],["ﯧ",237],["ﯨ",237],["ﯩﯪ",237],["ﯫ",237],["ﯬ",237],["ﯭ",237]],"14":[["ﯮ",237],["ﯯ",237],["ﯰ",237],["ﯱ",237],["ﯲ",237],["ﯳ",237],["ﯴ",237],["ﯵ",237],["ﯶ",237]],"15":[["ﯷ",237],["ﯸ",237],["ﯹ",237],["ﯺﯻ",237],["ﯼ",237],["ﯽ",237],["ﯾ",237],["ﯿ",237]]},"starts":[]}