{"lines":{"1":[["ﭑ",336],["ﭒ",336],["ﭓ",336],["ﭔ",336],["ﭕﭖ",336],["ﭗ",336],["ﭘ",336],["ﭙ",336],["ﭚ",336],["ﭛ",336],["ﭜ",336]],"2":[["ﭝ",336],["ﭞ",336],["ﭟ",336],["ﭠ",336],["ﭡ",336],["ﭢ",336],["ﭣ",336],["ﭤ",336],["ﭥ",336],["ﭦ",336]],"3":[["ﭧ",336],["ﭨ",336],["ﭩ",336],["ﭪ",336],["ﭫ",336],["ﭬ",336],["ﭭ",336],["ﭮ",336],["ﭯ",336],["ﭰ",336]],"4":[["ﭱ",336],["ﭲ",336],["ﭳ",336],["ﭴ",336],["ﭵ",336],["ﭶ",336],["ﭷ",336],["ﭸ",336],["ﭹ",336],["ﭺ",336],["ﭻ",336]],"5":[["ﭼ",336],["ﭽ",336],["ﭾ",336],["ﭿ",336],["ﮀ",336],["ﮁ",336],["ﮂ",336],["ﮃ",336]],"6":[["ﮄ",336],["ﮅ",336],["ﮆ",336],["ﮇ",336],["ﮈ",336],["ﮉ",336],["ﮊﮋ",336],["ﮌ",336],["ﮍ",336],["ﮎ",336]],"7":[["ﮏ",336],["ﮐﮑ",336],["ﮒ",336],["ﮓ",336],["ﮔ",336],["ﮕ",336],["ﮖ",336],["ﮗ",336],["ﮘ",336],["ﮙ",336]],"8":[["ﮚ",336],["ﮛ",336],["ﮜ",336],["ﮝ",336],["ﮞ",336],["ﮟ",336],["ﮠ",336],["ﮡ",336]],"9":[["ﮢ",336],["ﮣ",336],["ﮤ",336],["ﮥ",336],["ﮦ",336],["ﮧ",336],["ﮨ",336],["ﮩ",336]],"10":[["ﮪ",336],["ﮫ",336],["ﮬ",336],["ﮭﮮ",336],["ﮯ",336],["ﮰ",336],["ﮱ",336],["ﯓ",336],["ﯔﯕ",336],["ﯖ",336],["ﯗ",336]],"11":[["ﯘ",336],["ﯙ",336],["ﯚ",336],["ﯛ",336],["ﯜ",336],["ﯝﯞ",336],["ﯟ",336],["ﯠ",336]],"12":[["ﯡ",336],["ﯢ",336],["ﯣ",336],["ﯤ",336],["ﯥ",336],["ﯦ",336],["ﯧ",336],["ﯨ",336],["ﯩ",336],["ﯪ",336]],"13":[["ﯫ",336],["ﯬ",336],["ﯭ",336],["ﯮﯯ",336],["ﯰ",336],["ﯱ",336],["ﯲ",336],["ﯳ",336]],"14":[["ﯴ",336],["ﯵ",336],["ﯶ",336],["ﯷﯸ",336],["ﯹ",336],["ﯺ",336],["ﯻ",336],["ﯼﯽ",336],["ﯾ",336]],"15":[["ﯿ",336],["ﰀ",336],["ﰁ",336],["ﰂﰃ",336],["ﰄ",336],["ﰅ",336],["ﰆ",336],["ﰇ",336],["ﰈ",336],["ﰉ",336],["ﰊ",336],["ﰋ",336]]},"starts":[],"center":[]}