{"lines":{"1":[["ﭑ",439],["ﭒ",439],["ﭓ",439],["ﭔ",439],["ﭕ",439],["ﭖﭗ",439],["ﭘ",439],["ﭙ",439],["ﭚ",439],["ﭛﭜ",439],["ﭝ",439]],"2":[["ﭞ",439],["ﭟ",439],["ﭠ",439],["ﭡ",439],["ﭢ",439],["ﭣ",439],["ﭤﭥ",439],["ﭦ",439],["ﭧ",439],["ﭨ",439]],"3":[["ﭩ",439],["ﭪ",439],["ﭫ",439],["ﭬ",439],["ﭭ",439],["ﭮ",439],["ﭯ",439],["ﭰ",439],["ﭱ",439],["ﭲ",439]],"4":[["ﭳ",439],["ﭴ",439],["ﭵ",439],["ﭶ",439],["ﭷ",439],["ﭸ",439],["ﭹ",439],["ﭺ",439],["ﭻ",439],["ﭼ",439],["ﭽ",439],["ﭾ",439]],"5":[["ﭿ",439],["ﮀ",439],["ﮁ",439],["ﮂ",439],["ﮃ",439],["ﮄ",439],["ﮅﮆ",439],["ﮇ",439],["ﮈ",439],["ﮉ",439],["ﮊ",439]],"6":[["ﮋ",439],["ﮌ",439],["ﮍ",439],["ﮎ",439],["ﮏ",439],["ﮐ ﮑ",439],["ﮒ",439],["ﮓ",439],["ﮔ",439]],"7":[["ﮕ",439],["ﮖ",439],["ﮗﮘ",439],["ﮙ",439],["ﮚ",439],["ﮛ",439],["ﮜ",439],["ﮝ",439],["ﮞ",439],["ﮟ",439],["ﮠﮡ",439]],"8":[["ﮢ",439],["ﮣ",439],["ﮤ",439],["ﮥ",439],["ﮦ",439],["ﮧ",439],["ﮨ",439],["ﮩ",439],["ﮪ",439],["ﮫ",439]],"9":[["ﮬ",439],["ﮭ",439],["ﮮ",439],["ﮯ",439],["ﮰ",439],["ﮱ",439],["ﯓﯔ",439],["ﯕ",439],["ﯖ",439],["ﯗ",439]],"10":[["ﯘ",439],["ﯙ",439],["ﯚ",439],["ﯛ",439],["ﯜ",439],["ﯝ",439],["ﯞ",439],["ﯟ",439],["ﯠ",439],["ﯡﯢ",439]],"11":[["ﯣ",439],["ﯤ",439],["ﯥ",439],["ﯦ",439],["ﯧ",439],["ﯨﯩ",439],["ﯪ",439],["ﯫ",439],["ﯬ",439],["ﯭ",439]],"12":[["ﯮﯯ",439],["ﯰ",439],["ﯱ",439],["ﯲ",439],["ﯳ",439],["ﯴﯵ",439],["ﯶ",439],["ﯷ",439],["ﯸ",439],["ﯹ",439],["ﯺ",439]],"13":[["ﯻ",439],["ﯼ",439],["ﯽ",439],["ﯾ",439],["ﯿ",439],["ﰀ",439],["ﰁ",439],["ﰂ",439],["ﰃ",439],["ﰄ",439],["ﰅ",439]],"14":[["ﰆ",439],["ﰇ",439],["ﰈ",439],["ﰉ",439],["ﰊﰋ",439],["ﰌ",439],["ﰍ",439],["ﰎ",439],["ﰏ",439],["ﰐ",439],["ﰑ",439]],"15":[["ﰒ",439],["ﰓ",439],["ﰔ",439],["ﰕ",439],["ﰖﰗ",439],["ﰘ",439],["ﰙ",439],["ﰚ",439],["ﰛ",439],["ﰜ",439]]},"starts":[]}