{"1":"Когда разрушился небесный свод,","2":"Когда рассыпались все звезды","3":"И когда слили свои воды все моря,","4":"Когда перевернулися могилы, -","5":"(Тогда) познала каждая душа, Что было ею уготовано вперед, А что пришлось оставить (в жизни ближней).","6":"О человек! Какой соблазн (в жизни этой) Тебя от щедрого Владыки отвлекает -","7":"Того, Кто сотворил тебя, и выровнял, и соразмерил,","8":"И сотворил тебя в Ему угодном виде?","9":"Так нет! Считаете вы ложью Судный День.","10":"А ведь над вами - Его стражи,","11":"Исполненные доброты и чести И отмечающие все (деянья ваши), -","12":"Известно им все то, что вы вершите.","13":"Ведь будут праведники в благодати,","14":"А грешникам - гореть в Огне,","15":"Куда их в Судный День повергнут.","16":"И им не избежать его!","17":"Как объяснить тебе, что значит \"Судный День\"?","18":"И вновь, Как объяснить тебе, что значит \"Судный День\"?","19":"В тот День Не сможет ни одна душа Помочь другой хотя б на йоту; (Единственным) Владыкой Дня того Аллах предстанет!"}