{"1":"Когда небо разломится.","2":"Когда звезды рассыплются.","3":"И когда моря смешаются.","4":"И когда могилы перевернутся [и воскресшие рабы Аллаха покинут их] –","5":"каждый человек узнает, что он совершал [в земной жизни] и что оставил после себя [какова его участь в вечности].","6":"О человек! Что обмануло тебя относительно твоего Щедрого Господа?","7":"[Ведь Аллах – Тот] Кто сотворил тебя и придал тебе совершенное и соразмерное строение?","8":"Он придал тебе образ, какой пожелал.","9":"Но нет! Вы все равно не верите в воздаяние!","10":"И, поистине, у вас есть наблюдатели –","11":"благородные писцы.","12":"Они знают обо всем, что вы делаете.","13":"Поистине, праведники – в блаженстве.","14":"И, поистине, [неверующие] грешники – в Аду.","15":"Они войдут туда в День воздаяния.","16":"И они не выйдут оттуда.","17":"Откуда ты мог знать, что такое День воздаяния?","18":"Действительно, откуда ты мог знать, что такое День воздаяния?","19":"В тот день ни один человек ничем не поможет другому. И вся власть в тот день будет у Аллаха."}